README
setup.py
mian/__init__.py
mian/blocks.py
mian/mian.py
mian.egg-info/PKG-INFO
mian.egg-info/SOURCES.txt
mian.egg-info/dependency_links.txt
mian.egg-info/entry_points.txt
mian.egg-info/requires.txt
mian.egg-info/top_level.txt
test/test_package.py