Metadata-Version: 1.0
Name: mian
Version: 0.9.3
Summary: Graph blocks to height in a Minecraft save game
Home-page: https://github.com/l0b0/mian/wiki
Author: Victor Engmark
Author-email: victor.engmark@gmail.com
License: GPL v3 or newer
Download-URL: http://pypi.python.org/pypi/mian/
Keywords: Minecraft graph graphs block blocks
Platform: POSIX
Platform: Windows
Classifier: Development Status :: 3 - Alpha
Classifier: Environment :: Console
Classifier: Intended Audience :: End Users/Desktop
Classifier: License :: OSI Approved :: GNU General Public License (GPL)
Classifier: Operating System :: OS Independent
Classifier: Programming Language :: Python :: 2.6
Classifier: Topic :: Artistic Software
Classifier: Topic :: Multimedia :: Graphics
